gecos/__init__.py
gecos/gecos.py
gecos/version.py
ez_gecos-0.2.1.dist-info/LICENSE
ez_gecos-0.2.1.dist-info/METADATA
ez_gecos-0.2.1.dist-info/WHEEL
ez_gecos-0.2.1.dist-info/top_level.txt
ez_gecos-0.2.1.dist-info/RECORD
