Metadata-Version: 2.1
Name: ez-gecos
Version: 0.2.1
Summary: Tiny python package to parse the GECOS field.
Home-page: https://github.com/thohell/ez-gecos
Author: Thomas Hellström
Author-email: rel@xed.se
License: GPLv3
Platform: UNKNOWN
Classifier: Development Status :: 4 - Beta
Classifier: Intended Audience :: Developers
Classifier: License :: OSI Approved :: GNU General Public License v3 or later (GPLv3+)
Classifier: Programming Language :: Python :: 3.7
Classifier: Operating System :: POSIX :: Linux
Classifier: Topic :: Software Development :: Libraries :: Python Modules
